transformgpt/__init__.py
transformgpt/classify_main.py
transformgpt/source_utils.py
transformgpt/transform_main.py
transformgpt/transformgpt.py
transformgpt-0.1.3.data/scripts/classify_main.py
transformgpt-0.1.3.data/scripts/transform_main.py
transformgpt-0.1.3.dist-info/LICENSE
transformgpt-0.1.3.dist-info/METADATA
transformgpt-0.1.3.dist-info/WHEEL
transformgpt-0.1.3.dist-info/entry_points.txt
transformgpt-0.1.3.dist-info/top_level.txt
transformgpt-0.1.3.dist-info/RECORD
